bobtail/__init__.py
bobtail/exceptions.py
bobtail/form.py
bobtail/headers.py
bobtail/logger.py
bobtail/middleware.py
bobtail/options.py
bobtail/parser.py
bobtail/request.py
bobtail/response.py
bobtail/route.py
bobtail/static_files.py
bobtail/status.py
bobtail/wsgi.py
bobtail/wsgi_input.py
bobtail-0.2.2.dist-info/licenses/LICENSE.md
bobtail-0.2.2.dist-info/METADATA
bobtail-0.2.2.dist-info/WHEEL
bobtail-0.2.2.dist-info/top_level.txt
bobtail-0.2.2.dist-info/RECORD
